{
  "node": {
    "0020b8c8526c50ae8848b4c7414e1c5fe12eb6c280": {
      "workers": {
        "app/[locale]/patient/notifications/page": {
          "moduleId": 914477,
          "async": false,
          "exportedName": "getSettings",
          "filename": "src/app/[locale]/admin/settings/actions.ts"
        }
      },
      "exportedName": "getSettings",
      "filename": "src/app/[locale]/admin/settings/actions.ts"
    },
    "00e8f8d499616c05cdcb382c37b344e481bc72f143": {
      "workers": {
        "app/[locale]/patient/notifications/page": {
          "moduleId": 914477,
          "async": false,
          "exportedName": "getWebsiteContent",
          "filename": "src/app/[locale]/admin/settings/actions.ts"
        }
      },
      "exportedName": "getWebsiteContent",
      "filename": "src/app/[locale]/admin/settings/actions.ts"
    },
    "40f641790f2dfb8406f3b584b3a2ad3ef8aaf494d0": {
      "workers": {
        "app/[locale]/patient/notifications/page": {
          "moduleId": 914477,
          "async": false,
          "exportedName": "updateWebsiteContent",
          "filename": "src/app/[locale]/admin/settings/actions.ts"
        }
      },
      "exportedName": "updateWebsiteContent",
      "filename": "src/app/[locale]/admin/settings/actions.ts"
    },
    "40f67d8801e7eee62b97df7b4239d17050ceaca019": {
      "workers": {
        "app/[locale]/patient/notifications/page": {
          "moduleId": 914477,
          "async": false,
          "exportedName": "updateSettings",
          "filename": "src/app/[locale]/admin/settings/actions.ts"
        }
      },
      "exportedName": "updateSettings",
      "filename": "src/app/[locale]/admin/settings/actions.ts"
    }
  },
  "edge": {}
}